astrapay/__init__.py
astrapay/mpesa.py
astrapay-0.1.0.dist-info/METADATA
astrapay-0.1.0.dist-info/WHEEL
astrapay-0.1.0.dist-info/top_level.txt
astrapay-0.1.0.dist-info/RECORD
