Metadata-Version: 2.1
Name: astrapay
Version: 0.1.0
Summary: Lightweight Python SDK for M-Pesa STK Push by Astra Softwares
Home-page: https://github.com/astrasoft/astrapay
Author: Ishmael Bett
Author-email: info.astrasoft@gmail.com
License: MIT
Classifier: Programming Language :: Python :: 3
Classifier: Operating System :: OS Independent
Classifier: License :: OSI Approved :: MIT License
Classifier: Development Status :: 3 - Alpha
Requires-Python: >=3.6
Requires-Dist: requests
